LICENSE
MANIFEST.in
README.md
conf.py
index.rst
pyheapdump.rst
setup.cfg
setup.py
examples/crash_with_threads.py
examples/dump_on_unhandled_exceptions.pth
pydevd_archives/README.txt
pyheapdump/__init__.py
pyheapdump/__main__.py
pyheapdump/_pyheapdump.py
pyheapdump/test_pyheapdump.py
pyheapdump.egg-info/PKG-INFO
pyheapdump.egg-info/SOURCES.txt
pyheapdump.egg-info/dependency_links.txt
pyheapdump.egg-info/requires.txt
pyheapdump.egg-info/top_level.txt